BuscaTuPokemon/__init__.py
BuscaTuPokemon/pokemon.csv
BuscaTuPokemon/random_pokemon.py
BuscaTuPokemon-1.0.1.dist-info/METADATA
BuscaTuPokemon-1.0.1.dist-info/WHEEL
BuscaTuPokemon-1.0.1.dist-info/top_level.txt
BuscaTuPokemon-1.0.1.dist-info/RECORD
